sticky_note_organizer-1.1.0.dist-info/licenses/LICENSE
sticky_organizer/__init__.py
sticky_organizer/analytics.py
sticky_organizer/backup.py
sticky_organizer/categorizer.py
sticky_organizer/cli.py
sticky_organizer/database.py
sticky_organizer/editor.py
sticky_organizer/exporters.py
sticky_organizer/filters.py
sticky_organizer/gui.py
sticky_organizer/gui_launcher.py
sticky_note_organizer-1.1.0.dist-info/METADATA
sticky_note_organizer-1.1.0.dist-info/WHEEL
sticky_note_organizer-1.1.0.dist-info/entry_points.txt
sticky_note_organizer-1.1.0.dist-info/top_level.txt
sticky_note_organizer-1.1.0.dist-info/RECORD
