Metadata-Version: 2.4
Name: sticky-note-organizer
Version: 1.1.0
Summary: A powerful CLI and GUI tool to extract, organize, and analyze Microsoft Sticky Notes (modern and classic formats)
Home-page: https://github.com/Primus-Izzy/Sticky-Note-Organizer
Author: Primus-Izzy
Author-email: 
Classifier: Development Status :: 4 - Beta
Classifier: Intended Audience :: End Users/Desktop
Classifier: License :: OSI Approved :: MIT License
Classifier: Operating System :: OS Independent
Classifier: Programming Language :: Python :: 3
Classifier: Programming Language :: Python :: 3.7
Classifier: Programming Language :: Python :: 3.8
Classifier: Programming Language :: Python :: 3.9
Classifier: Programming Language :: Python :: 3.10
Classifier: Programming Language :: Python :: 3.11
Requires-Python: >=3.7
License-File: LICENSE
Requires-Dist: click>=8.0.0
Requires-Dist: pandas>=1.3.0
Requires-Dist: openpyxl>=3.0.0
Requires-Dist: colorama>=0.4.0
Requires-Dist: tabulate>=0.8.0
Requires-Dist: pathlib2>=2.3.0
Requires-Dist: python-dateutil>=2.8.0
Requires-Dist: matplotlib>=3.5.0
Requires-Dist: Pillow>=9.0.0
Requires-Dist: wordcloud>=1.8.0
Dynamic: author
Dynamic: classifier
Dynamic: description
Dynamic: description-content-type
Dynamic: home-page
Dynamic: license-file
Dynamic: requires-dist
Dynamic: requires-python
Dynamic: summary
